MANIFEST.in
README.md
setup.py
djsourceview/__init__.py
djsourceview/urls.py
djsourceview/views.py
djsourceview.egg-info/PKG-INFO
djsourceview.egg-info/SOURCES.txt
djsourceview.egg-info/dependency_links.txt
djsourceview.egg-info/requires.txt
djsourceview.egg-info/top_level.txt
djsourceview.egg-info/zip-safe
djsourceview/static/djsourceview/prism.css
djsourceview/static/djsourceview/prism.js
djsourceview/templates/djsourceview.html