Metadata-Version: 1.1
Name: djsourceview
Version: 0.1.4
Summary: Module for Django to view the javascript source code and html
Home-page: https://github.com/rogerboff/djsourceview
Author: Roger Pereira Boff
Author-email: rogerboff@gmail.com
License: MIT License
Keywords: django,djsourceview
Platform: OS Independent
Classifier: Development Status :: 4 - Beta
Classifier: Operating System :: OS Independent
Classifier: Programming Language :: Python
Classifier: Environment :: Web Environment
Classifier: Framework :: Django
Classifier: Intended Audience :: Developers
Classifier: License :: OSI Approved :: MIT License
Classifier: Topic :: Software Development :: Libraries :: Python Modules
Classifier: Programming Language :: Python :: 2.7
